j_test/__init__.py
j_test/janome_test.py
j_test-1.0.2.dist-info/METADATA
j_test-1.0.2.dist-info/WHEEL
j_test-1.0.2.dist-info/top_level.txt
j_test-1.0.2.dist-info/RECORD
