Metadata-Version: 2.1
Name: j-test
Version: 1.0.2
Summary: A sample Python project
Home-page: UNKNOWN
Author: kako
Author-email: 
License: UNKNOWN
Platform: UNKNOWN
Requires-Python: >=2.7, !=3.0.*, !=3.1.*, !=3.2.*, !=3.3.*, <4
Requires-Dist: janome
